astropy/CITATION
astropy/__init__.py
astropy/_compiler.c
astropy/_version.py
astropy/compiler_version.cp311-win_amd64.pyd
astropy/conftest.py
astropy/logger.py
astropy/version.py
astropy/config/__init__.py
astropy/config/configuration.py
astropy/config/paths.py
astropy/config/tests/__init__.py
astropy/config/tests/test_configs.py
astropy/config/tests/data/alias.cfg
astropy/config/tests/data/deprecated.cfg
astropy/config/tests/data/empty.cfg
astropy/config/tests/data/not_empty.cfg
astropy/constants/__init__.py
astropy/constants/astropyconst13.py
astropy/constants/astropyconst20.py
astropy/constants/astropyconst40.py
astropy/constants/cgs.py
astropy/constants/codata2010.py
astropy/constants/codata2014.py
astropy/constants/codata2018.py
astropy/constants/config.py
astropy/constants/constant.py
astropy/constants/iau2012.py
astropy/constants/iau2015.py
astropy/constants/si.py
astropy/constants/utils.py
astropy/constants/tests/__init__.py
astropy/constants/tests/test_constant.py
astropy/constants/tests/test_pickle.py
astropy/constants/tests/test_prior_version.py
astropy/constants/tests/test_sciencestate.py
astropy/convolution/__init__.py
astropy/convolution/_convolve.cp311-win_amd64.pyd
astropy/convolution/_convolve.pyx
astropy/convolution/convolve.py
astropy/convolution/core.py
astropy/convolution/kernels.py
astropy/convolution/setup_package.py
astropy/convolution/utils.py
astropy/convolution/src/convolve.c
astropy/convolution/src/convolve.h
astropy/convolution/tests/__init__.py
astropy/convolution/tests/test_convolve.py
astropy/convolution/tests/test_convolve_fft.py
astropy/convolution/tests/test_convolve_kernels.py
astropy/convolution/tests/test_convolve_models.py
astropy/convolution/tests/test_convolve_nddata.py
astropy/convolution/tests/test_discretize.py
astropy/convolution/tests/test_kernel_class.py
astropy/convolution/tests/test_pickle.py
astropy/coordinates/__init__.py
astropy/coordinates/attributes.py
astropy/coordinates/baseframe.py
astropy-7.1.1.dist-info/licenses/LICENSE.rst
astropy-7.1.1.dist-info/licenses/licenses/AURA_LICENSE.rst
astropy-7.1.1.dist-info/licenses/licenses/CONFIGOBJ_LICENSE.rst
astropy-7.1.1.dist-info/licenses/licenses/DATATABLES_LICENSE.rst
astropy-7.1.1.dist-info/licenses/licenses/ERFA.rst
astropy-7.1.1.dist-info/licenses/licenses/EXPAT_LICENSE.rst
astropy-7.1.1.dist-info/licenses/licenses/GATSPY_LICENSE.rst
astropy-7.1.1.dist-info/licenses/licenses/JQUERY_LICENSE.rst
astropy-7.1.1.dist-info/licenses/licenses/NUMPY_LICENSE.rst
astropy-7.1.1.dist-info/licenses/licenses/PLY_LICENSE.rst
astropy-7.1.1.dist-info/licenses/licenses/POSITIONAL_DEFAULTS.rst
astropy-7.1.1.dist-info/licenses/licenses/PYFITS.rst
astropy-7.1.1.dist-info/licenses/licenses/PYTHON.rst
astropy-7.1.1.dist-info/licenses/licenses/README.rst
astropy-7.1.1.dist-info/licenses/licenses/WCSLIB_LICENSE.rst
astropy-7.1.1.dist-info/METADATA
astropy-7.1.1.dist-info/WHEEL
astropy-7.1.1.dist-info/entry_points.txt
astropy-7.1.1.dist-info/top_level.txt
astropy-7.1.1.dist-info/RECORD
