Metadata-Version: 2.4
Name: astropy
Version: 7.1.1
Summary: Astronomy and astrophysics core library
Author-email: The Astropy Developers <astropy.team@gmail.com>
License-Expression: BSD-3-Clause
Project-URL: homepage, https://www.astropy.org/
Project-URL: documentation, https://docs.astropy.org
Project-URL: repository, https://github.com/astropy/astropy
Keywords: astronomy,astrophysics,cosmology,space,science,units,table,wcs,samp,coordinate,fits,modeling,models,fitting,ascii
Classifier: Intended Audience :: Science/Research
Classifier: Operating System :: OS Independent
Classifier: Programming Language :: C
Classifier: Programming Language :: Cython
Classifier: Programming Language :: Python :: 3 :: Only
Classifier: Programming Language :: Python :: 3.11
Classifier: Programming Language :: Python :: 3.12
Classifier: Programming Language :: Python :: 3.13
Classifier: Programming Language :: Python :: Implementation :: CPython
Classifier: Topic :: Scientific/Engineering :: Astronomy
Classifier: Topic :: Scientific/Engineering :: Physics
Requires-Python: >=3.11
License-File: LICENSE.rst
License-File: licenses/AURA_LICENSE.rst
License-File: licenses/CONFIGOBJ_LICENSE.rst
License-File: licenses/DATATABLES_LICENSE.rst
License-File: licenses/ERFA.rst
License-File: licenses/EXPAT_LICENSE.rst
License-File: licenses/GATSPY_LICENSE.rst
License-File: licenses/JQUERY_LICENSE.rst
License-File: licenses/NUMPY_LICENSE.rst
License-File: licenses/PLY_LICENSE.rst
License-File: licenses/POSITIONAL_DEFAULTS.rst
License-File: licenses/PYFITS.rst
License-File: licenses/PYTHON.rst
License-File: licenses/README.rst
License-File: licenses/WCSLIB_LICENSE.rst
Requires-Dist: numpy>=1.23.2
Requires-Dist: pyerfa>=2.0.1.1
Requires-Dist: astropy-iers-data>=0.2025.9.29.0.35.48
Requires-Dist: PyYAML>=6.0.0
Requires-Dist: packaging>=22.0.0
Provides-Extra: recommended
Requires-Dist: scipy>=1.9.2; extra == "recommended"
Requires-Dist: matplotlib>=3.6.0; extra == "recommended"
Provides-Extra: ipython
Requires-Dist: ipython>=8.0.0; extra == "ipython"
Provides-Extra: jupyter
Requires-Dist: astropy[ipython]; extra == "jupyter"
Requires-Dist: ipywidgets>=7.7.3; extra == "jupyter"
Requires-Dist: ipykernel>=6.16.0; extra == "jupyter"
Requires-Dist: ipydatagrid>=1.1.13; extra == "jupyter"
Requires-Dist: jupyter-core>=4.11.2; extra == "jupyter"
Requires-Dist: pandas>=1.5.0; extra == "jupyter"
Provides-Extra: all
Requires-Dist: astropy[recommended]; extra == "all"
Requires-Dist: astropy[ipython]; extra == "all"
Requires-Dist: astropy[jupyter]; extra == "all"
Requires-Dist: certifi>=2022.6.15.1; extra == "all"
Requires-Dist: dask[array]>=2022.5.1; extra == "all"
Requires-Dist: h5py>=3.8.0; extra == "all"
Requires-Dist: pyarrow>=10.0.1; extra == "all"
Requires-Dist: beautifulsoup4>=4.9.3; extra == "all"
Requires-Dist: html5lib>=1.1; extra == "all"
Requires-Dist: bleach>=3.2.1; extra == "all"
Requires-Dist: pandas>=2.0; extra == "all"
Requires-Dist: sortedcontainers>=1.5.7; extra == "all"
Requires-Dist: pytz>=2016.10; extra == "all"
Requires-Dist: jplephem>=2.6; extra == "all"
Requires-Dist: mpmath>=1.2.1; extra == "all"
Requires-Dist: asdf>=2.8.3; extra == "all"
Requires-Dist: asdf-astropy>=0.3; extra == "all"
Requires-Dist: bottleneck>=1.3.3; extra == "all"
Requires-Dist: fsspec[http]>=2023.4.0; extra == "all"
Requires-Dist: s3fs>=2023.4.0; extra == "all"
Requires-Dist: uncompresspy>=0.4.0; extra == "all"
Provides-Extra: test
Requires-Dist: coverage>=6.4.4; extra == "test"
Requires-Dist: pre-commit>=2.9.3; extra == "test"
Requires-Dist: pytest>=8.0.0; extra == "test"
Requires-Dist: pytest-doctestplus>=1.4.0; extra == "test"
Requires-Dist: pytest-astropy-header>=0.2.1; extra == "test"
Requires-Dist: pytest-astropy>=0.10.0; extra == "test"
Requires-Dist: pytest-xdist>=2.5.0; extra == "test"
Requires-Dist: threadpoolctl>=3.0.0; extra == "test"
Provides-Extra: test-all
Requires-Dist: astropy[all]; extra == "test-all"
Requires-Dist: astropy[test]; extra == "test-all"
Requires-Dist: objgraph>=1.6.0; extra == "test-all"
Requires-Dist: skyfield>=1.20; extra == "test-all"
Requires-Dist: sgp4>=2.3; extra == "test-all"
Requires-Dist: array-api-strict>=1.0; extra == "test-all"
Requires-Dist: array-api-strict<2.4; python_version < "3.12" and extra == "test-all"
Provides-Extra: typing
Requires-Dist: pandas-stubs>=2.0; extra == "typing"
Provides-Extra: docs
Requires-Dist: astropy[recommended]; extra == "docs"
Requires-Dist: sphinx; extra == "docs"
Requires-Dist: sphinx-astropy[confv2]>=1.9.1; extra == "docs"
Requires-Dist: pytest>=8.0.0; extra == "docs"
Requires-Dist: sphinx-changelog>=1.2.0; extra == "docs"
Requires-Dist: sphinx_design; extra == "docs"
Requires-Dist: Jinja2>=3.1.3; extra == "docs"
Requires-Dist: sphinxcontrib-globalsubs>=0.1.1; extra == "docs"
Requires-Dist: matplotlib>=3.9.1; extra == "docs"
Provides-Extra: dev
Requires-Dist: astropy[recommended]; extra == "dev"
Requires-Dist: astropy[test]; extra == "dev"
Requires-Dist: astropy[docs]; extra == "dev"
Requires-Dist: astropy[typing]; extra == "dev"
Provides-Extra: dev-all
Requires-Dist: tox; extra == "dev-all"
Requires-Dist: astropy[dev]; extra == "dev-all"
Requires-Dist: astropy[test_all]; extra == "dev-all"
Dynamic: license-file
